lwilbert/Neural_Network.py
lwilbert/__init__.py
lwilbert/__main__.py
LW-0.0.2.dist-info/METADATA
LW-0.0.2.dist-info/WHEEL
LW-0.0.2.dist-info/top_level.txt
LW-0.0.2.dist-info/RECORD
