Metadata-Version: 2.1
Name: LW
Version: 0.0.2
Summary: A Group of Packages by Luis Wilbert
Home-page: UNKNOWN
Author: Luis Eduardo Wilbert Albernaz Andrade
Author-email: wilbert@mit.edu
License: UNKNOWN
Keywords: Supply Chain Managemento,SCM
Platform: UNKNOWN
Classifier: Development Status :: 3 - Alpha
Classifier: Intended Audience :: Developers
Classifier: Topic :: Software Development :: Build Tools
Classifier: License :: OSI Approved :: MIT License
Classifier: Programming Language :: Python :: 3
Classifier: Programming Language :: Python :: 3.5
Classifier: Programming Language :: Python :: 3.6
Classifier: Programming Language :: Python :: 3.7
Classifier: Programming Language :: Python :: 3.8
Classifier: Programming Language :: Python :: 3 :: Only
Requires-Python: >=3.5, <4
Requires-Dist: numpy
Requires-Dist: pandas
